myo_tools/__init__.py
myo_tools/examples/examine_marker.py
myo_tools/examples/examine_mj.py
myo_tools/mj/__init__.py
myo_tools/mj/core/__init__.py
myo_tools/mj/core/mj_api.py
myo_tools/mjs/__init__.py
myo_tools/mjs/core/__init__.py
myo_tools/mjs/core/mjs_api.py
myo_tools/mjs/marker/__init__.py
myo_tools/mjs/marker/marker_api.py
myo_tools/utils/__init__.py
myo_tools/utils/file_ops/__init__.py
myo_tools/utils/file_ops/dataframe_utils.py
myo_tools/utils/file_ops/import_utils.py
myo_tools/utils/file_ops/io_utils.py
myo_tools/utils/file_ops/xml_utils.py
myo_tools/utils/log_ops/__init__.py
myo_tools/utils/log_ops/logger.py
myo_tools/utils/mocap_ops/__init__.py
myo_tools/utils/mocap_ops/c3d_utils.py
myo_tools/utils/mocap_ops/mocap_utils.py
myo_tools/utils/mocap_ops/trc_utils.py
myo_tools/utils/tensor_ops/__init__.py
myo_tools/utils/tensor_ops/dict_utils.py
myo_tools/utils/tensor_ops/quat_utils.py
myo_tools/utils/tensor_ops/tensor_utils.py
myo_tools-0.1.1.dist-info/METADATA
myo_tools-0.1.1.dist-info/WHEEL
myo_tools-0.1.1.dist-info/top_level.txt
myo_tools-0.1.1.dist-info/RECORD
