Metadata-Version: 2.4
Name: myo_tools
Version: 0.1.1
Summary: A Python package for the myo api.
Author: myolab
Requires-Python: >=3.8
Requires-Dist: numpy
Requires-Dist: mujoco==3.3.3
Requires-Dist: lxml
Requires-Dist: ezc3d
Requires-Dist: c3d
Requires-Dist: GitPython
Requires-Dist: scipy
Requires-Dist: pandas
Requires-Dist: pyarrow
Provides-Extra: dev
Requires-Dist: pre-commit; extra == "dev"
Requires-Dist: pytest; extra == "dev"
Requires-Dist: click; extra == "dev"
Requires-Dist: requests; extra == "dev"
Provides-Extra: test
Requires-Dist: pytest; extra == "test"
Requires-Dist: click; extra == "test"
Requires-Dist: mujoco-mjx==3.3.3; extra == "test"
